circuitpython/__init__.py
circuitpython/circuits/basic_functions.py
circuitpython/circuits/mesh_current.py
circuitpython/circuits/node_voltage.py
circuitpython/circuits/resistance.py
circuitpython/circuits/thevenin_norton.py
circuitpython/digitals/binary.py
circuitpython/digitals/simplify_logic.py
circuitpython/digitals/truth_table.py
circuitpython/sensory/pt100.py
circuitpython/sensory/wheatstone.py
circuitpython-0.1.5.dist-info/licenses/LICENSE
circuitpython-0.1.5.dist-info/METADATA
circuitpython-0.1.5.dist-info/WHEEL
circuitpython-0.1.5.dist-info/top_level.txt
circuitpython-0.1.5.dist-info/RECORD
